mercurius/__init__.py
mercurius/data/__init__.py
mercurius/data/candlereader.py
mercurius/strategy/__init__.py
mercurius/strategy/anticor.py
mercurius/strategy/anticor2.py
mercurius/strategy/anticort.py
mercurius/strategy/base.py
mercurius/strategy/bcrp.py
mercurius/strategy/best.py
mercurius/strategy/bk.py
mercurius/strategy/bnn.py
mercurius/strategy/cornk.py
mercurius/strategy/cornu.py
mercurius/strategy/cwmr.py
mercurius/strategy/cwmr_std.py
mercurius/strategy/cwmr_var.py
mercurius/strategy/eg.py
mercurius/strategy/m0.py
mercurius/strategy/olmar.py
mercurius/strategy/olmar2.py
mercurius/strategy/ons.py
mercurius/strategy/pamr.py
mercurius/strategy/pamr_deprecated.py
mercurius/strategy/rmr.py
mercurius/strategy/rmr2.py
mercurius/strategy/sp.py
mercurius/strategy/tools.py
mercurius/strategy/ubah.py
mercurius/strategy/ucrp.py
mercurius/strategy/up.py
mercurius/strategy/wmamr.py
mercurius/utils/__init__.py
mercurius/utils/indicators.py
mercurius/web/__init__.py
mercurius/web/app.py
mercurius-0.0.1.dist-info/LICENSE
mercurius-0.0.1.dist-info/METADATA
mercurius-0.0.1.dist-info/WHEEL
mercurius-0.0.1.dist-info/top_level.txt
mercurius-0.0.1.dist-info/RECORD
