Metadata-Version: 2.1
Name: mercurius
Version: 0.0.1
Summary: Yet Another Portfolio Management Toolbox
Home-page: https://github.com/dexhunter/mercurius-dev
Author: Dixing (Dex) Xu
Author-email: dixingxu@gmail.com
License: UNKNOWN
Platform: UNKNOWN
Requires-Dist: pandas
Requires-Dist: xarray
Requires-Dist: tensorflow
Requires-Dist: numpy
Requires-Dist: ccxt
Requires-Dist: requests
Requires-Dist: flask
Requires-Dist: flask-cors
Requires-Dist: flask-socketio
Requires-Dist: matplotlib
Requires-Dist: scipy
Requires-Dist: sqlalchemy
Requires-Dist: cvxopt
